dotviewer/__init__.py
dotviewer/conftest.py
dotviewer/dotviewer.py
dotviewer/drawgraph.py
dotviewer/graphclient.py
dotviewer/graphdisplay.py
dotviewer/graphpage.py
dotviewer/graphparse.py
dotviewer/graphserver.py
dotviewer/msgstruct.py
dotviewer/sshgraphserver.py
dotviewer/strunicode.py
dotviewer/test/__init__.py
dotviewer/test/test_interactive.py
dotviewer/test/test_interactive_unicode.py
dotviewer/test/test_msgstruct.py
dotviewer/test/test_translator.py
dotviewer/test/test_unicode_util.py
rpython/__init__.py
rpython/__main__.py
rpython/conftest.py
rpython/annotator/__init__.py
rpython/annotator/annrpython.py
rpython/annotator/argument.py
rpython/annotator/binaryop.py
rpython/annotator/bookkeeper.py
rpython/annotator/builtin.py
rpython/annotator/classdesc.py
rpython/annotator/description.py
rpython/annotator/dictdef.py
rpython/annotator/exception.py
rpython/annotator/listdef.py
rpython/annotator/model.py
rpython/annotator/policy.py
rpython/annotator/signature.py
rpython/annotator/specialize.py
rpython/annotator/unaryop.py
rpython/annotator/test/__init__.py
rpython/annotator/test/test_annrpython.py
rpython/annotator/test/test_annsimplifyrpython.py
rpython/annotator/test/test_argument.py
rpython/annotator/test/test_description.py
rpython/annotator/test/test_model.py
rpython/annotator/test/test_signature.py
rpython/config/__init__.py
rpython/config/config.py
rpython/config/parse.py
rpython/config/support.py
rpython/config/translationoption.py
rpython/flowspace/__init__.py
rpython/flowspace/argument.py
rpython/flowspace/bytecode.py
rpython/flowspace/flowcontext.py
rpython/flowspace/framestate.py
rpython/flowspace/generator.py
rpython/flowspace/model.py
rpython/flowspace/objspace.py
rpython/flowspace/operation.py
rpython/flowspace/pygraph.py
rpython/flowspace/specialcase.py
rpython/flowspace/test/__init__.py
rpython/flowspace/test/cant_import.py
rpython/flowspace/test/test_argument.py
rpython-0.2.1.dist-info/DESCRIPTION.rst
rpython-0.2.1.dist-info/METADATA
rpython-0.2.1.dist-info/RECORD
rpython-0.2.1.dist-info/WHEEL
rpython-0.2.1.dist-info/entry_points.txt
rpython-0.2.1.dist-info/metadata.json
rpython-0.2.1.dist-info/top_level.txt
