Metadata-Version: 2.0
Name: rpython
Version: 0.2.1
Summary: RPython
Home-page: https://rpython.readthedocs.org
Author: The PyPy team
Author-email: pypy-dev@python.org
License: MIT
Keywords: development
Platform: UNKNOWN
Classifier: Development Status :: 3 - Alpha
Classifier: Intended Audience :: Developers
Classifier: Topic :: Software Development :: Build Tools
Classifier: License :: OSI Approved :: MIT License
Classifier: Programming Language :: Python :: 2
Classifier: Programming Language :: Python :: 2.6
Classifier: Programming Language :: Python :: 2.7
Requires-Dist: pytest (<3)
